MANIFEST.in
bootstrap.py
buildout.cfg
setup.py
docs/CREDITS.TXT
docs/LICENSE.GPL
docs/LICENSE.txt
docs/tutorial.txt
kssexamples/__init__.py
kssexamples/ajax.py
kssexamples/development.py
kssexamples/production.py
kssexamples/settings.py
kssexamples/urls.py
kssexamples/views.py
kssexamples/media/time_of_day.kss
kssexamples/templates/404.html
kssexamples/templates/time_of_day.html
src/kss/__init__.py
src/kss.django.egg-info/PKG-INFO
src/kss.django.egg-info/SOURCES.txt
src/kss.django.egg-info/dependency_links.txt
src/kss.django.egg-info/not-zip-safe
src/kss.django.egg-info/requires.txt
src/kss.django.egg-info/top_level.txt
src/kss/django/__init__.py
src/kss/django/setup.py
src/kss/django/setup.txt
src/kss/django/shortcuts.py
src/kss/django/shortcuts.txt
src/kss/django/templatetags.txt
src/kss/django/tests.py
src/kss/django/urls.py
src/kss/django/views.py
src/kss/django/views.txt
src/kss/django/templatetags/__init__.py
src/kss/django/templatetags/ksstags.py
