Metadata-Version: 1.0
Name: kss.django
Version: 0.1
Summary: KSS for Django
Home-page: UNKNOWN
Author: UNKNOWN
Author-email: UNKNOWN
License: UNKNOWN
Platform: UNKNOWN
